<annotation>
	<folder>black-box</folder>
	<filename>21.jpg</filename>
	<path>D:\project\food box\box picture\black-box\21.jpg</path>
	<source>
		<database>Unknown</database>
	</source>
	<size>
		<width>640</width>
		<height>480</height>
		<depth>3</depth>
	</size>
	<segmented>0</segmented>
	<object>
		<name>black-box</name>
		<pose>Unspecified</pose>
		<truncated>0</truncated>
		<difficult>0</difficult>
		<bndbox>
			<xmin>43</xmin>
			<ymin>50</ymin>
			<xmax>613</xmax>
			<ymax>332</ymax>
		</bndbox>
	</object>
</annotation>
